ftpservx-0.5.7.dist-info/DESCRIPTION.rst
ftpservx-0.5.7.dist-info/entry_points.txt
ftpservx-0.5.7.dist-info/METADATA
ftpservx-0.5.7.dist-info/WHEEL
ftpservx-0.5.7.dist-info/metadata.json
ftpservx-0.5.7.dist-info/top_level.txt
ftpservx-0.5.7.dist-info/RECORD
ftpservx/main.py
ftpservx/__init__.py
